{"type": "Feature", "id": 12511134, "properties": {"woe:id": 12511134, "woe:parent_id": 459070, "woe:name": "Aeroporto Fazenda Ilha Camargo", "woe:placetype": 14, "woe:placetype_name": "Airport", "woe:lang": "POR", "iso:country": "BR", "meta:provider": ["geoplanet:7.3.1", "geoplanet:7.3.2", "geoplanet:7.4.0", "geoplanet:7.4.1", "geoplanet:7.5.1", "geoplanet:7.5.2", "geoplanet:7.6.0", "geoplanet:7.8.1", "geoplanet:7.9.0", "geoplanet:7.10.0", "geoplanet:8.0.0", "woeplanet:8.0.0"], "meta:indexed": "2020-08-20T20:58:25.890651", "meta:updated": "2020-08-22T02:59:07.233613", "woe:alias_ENG_P": ["Fazenda Ilha Camargo Airport"], "woe:hierarchy": {"continent": 24865673, "country": 23424768, "town": 0, "planet": 1, "county": 12579323, "suburb": 0, "state": 2344855, "region": 0, "localadmin": 0}, "woe:timezone_id": 56043575, "woe:hash": "6szybmkekt8b", "woe:centroid": [-56.584202, -17.0653], "geom:latitude": -17.0653, "geom:longitude": -56.584202, "geom:hash": "6szybmkekt8b", "woe:latitude": -17.0653, "geom:centroid": [-56.584202, -17.0653], "woe:longitude": -56.584202, "woe:repo": "woeplanet-airport-br"}, "geometry": {"coordinates": [-56.584202, -17.0653], "type": "Point"}}