{"type": "Feature", "id": 12511249, "properties": {"woe:id": 12511249, "woe:parent_id": 456369, "woe:name": "Aeroporto Oiapoque", "woe:placetype": 14, "woe:placetype_name": "Airport", "woe:lang": "POR", "iso:country": "BR", "meta:provider": ["geoplanet:7.3.1", "geoplanet:7.3.2", "geoplanet:7.4.0", "geoplanet:7.4.1", "geoplanet:7.5.1", "geoplanet:7.5.2", "geoplanet:7.6.0", "geoplanet:7.8.1", "geoplanet:7.9.0", "geoplanet:7.10.0", "geoplanet:8.0.0", "woeplanet:8.0.0"], "meta:indexed": "2020-08-20T20:58:25.987015", "woe:alias_ENG_V": ["OYK Airport", "OYK"], "woe:alias_POR_V": ["Aeroporto OYK"], "meta:updated": "2020-08-22T02:59:07.276032", "woe:alias_ENG_P": ["Oiapoque Airport"], "woe:hierarchy": {"continent": 24865673, "country": 23424768, "town": 0, "planet": 1, "county": 12578166, "suburb": 0, "state": 2344846, "region": 0, "localadmin": 0}, "woe:timezone_id": 56043569, "woe:hash": "dbejud6w3ktq", "woe:centroid": [-51.830002, 3.8367], "geom:latitude": 3.8367, "geom:longitude": -51.830002, "geom:hash": "dbejud6w3ktq", "woe:latitude": 3.8367, "geom:centroid": [-51.830002, 3.8367], "woe:longitude": -51.830002, "woe:repo": "woeplanet-airport-br"}, "geometry": {"coordinates": [-51.830002, 3.8367], "type": "Point"}}