{"type": "Feature", "id": 12523482, "properties": {"woe:id": 12523482, "woe:parent_id": 422488, "woe:name": "Aeroporto Aripuana", "woe:placetype": 14, "woe:placetype_name": "Airport", "woe:lang": "POR", "iso:country": "BR", "meta:provider": ["geoplanet:7.3.1", "geoplanet:7.3.2", "geoplanet:7.4.0", "geoplanet:7.4.1", "geoplanet:7.5.1", "geoplanet:7.5.2", "geoplanet:7.6.0", "geoplanet:7.8.1", "geoplanet:7.9.0", "geoplanet:7.10.0", "geoplanet:8.0.0", "woeplanet:8.0.0"], "meta:indexed": "2020-08-20T20:58:26.102155", "meta:updated": "2020-08-22T02:59:07.323700", "woe:alias_ENG_P": ["Aripuana Airport"], "woe:hierarchy": {"continent": 24865673, "country": 23424768, "town": 0, "planet": 1, "county": 12579322, "suburb": 0, "state": 2344855, "region": 0, "localadmin": 0}, "woe:timezone_id": 56043575, "woe:hash": "6wjz4we51cgz", "woe:centroid": [-59.299999, -9.9833], "geom:latitude": -9.9833, "geom:longitude": -59.299999, "geom:hash": "6wjz4we51cgz", "woe:latitude": -9.9833, "geom:centroid": [-59.299999, -9.9833], "woe:longitude": -59.299999, "woe:repo": "woeplanet-airport-br"}, "geometry": {"coordinates": [-59.299999, -9.9833], "type": "Point"}}