{"type": "Feature", "id": 12523583, "properties": {"woe:id": 12523583, "woe:parent_id": 455954, "woe:name": "Aeroporto J. Batista Bos Filho", "woe:placetype": 14, "woe:placetype_name": "Airport", "woe:lang": "POR", "iso:country": "BR", "meta:provider": ["geoplanet:7.3.1", "geoplanet:7.3.2", "geoplanet:7.4.0", "geoplanet:7.4.1", "geoplanet:7.5.1", "geoplanet:7.5.2", "geoplanet:7.6.0", "geoplanet:7.8.1", "geoplanet:7.9.0", "geoplanet:7.10.0", "geoplanet:8.0.0", "woeplanet:8.0.0"], "meta:indexed": "2020-08-20T20:58:26.122479", "woe:alias_ENG_V": ["IJU Airport", "IJU"], "woe:alias_POR_V": ["Aeroporto IJU"], "meta:updated": "2020-08-22T02:59:07.332187", "woe:alias_ENG_P": ["J. Batista Bos Filho Airport"], "woe:hierarchy": {"continent": 24865673, "country": 23424768, "town": 0, "planet": 1, "county": 12581375, "suburb": 0, "state": 2344864, "region": 0, "localadmin": 0}, "woe:timezone_id": 28350792, "woe:hash": "6fcwm4gh9zhj", "woe:centroid": [-53.916698, -28.4167], "geom:latitude": -28.4167, "geom:longitude": -53.916698, "geom:hash": "6fcwm4gh9zhj", "woe:latitude": -28.4167, "geom:centroid": [-53.916698, -28.4167], "woe:longitude": -53.916698, "woe:repo": "woeplanet-airport-br"}, "geometry": {"coordinates": [-53.916698, -28.4167], "type": "Point"}}