{"type": "Feature", "id": 12523476, "properties": {"woe:id": 12523476, "woe:parent_id": 455841, "woe:name": "Aeroporto Arapiraca", "woe:placetype": 14, "woe:placetype_name": "Airport", "woe:lang": "POR", "iso:country": "BR", "meta:provider": ["geoplanet:7.3.1", "geoplanet:7.3.2", "geoplanet:7.4.0", "geoplanet:7.4.1", "geoplanet:7.5.1", "geoplanet:7.5.2", "geoplanet:7.6.0", "geoplanet:7.8.1", "geoplanet:7.9.0", "geoplanet:7.10.0", "geoplanet:8.0.0", "woeplanet:8.0.0"], "meta:indexed": "2020-08-20T20:58:26.101295", "woe:alias_ENG_V": ["APQ Airport", "APQ"], "woe:alias_POR_V": ["Aeroporto APQ"], "meta:updated": "2020-08-22T02:59:07.323359", "woe:alias_ENG_P": ["Arapiraca Airport"], "woe:hierarchy": {"continent": 24865673, "country": 23424768, "town": 0, "planet": 1, "county": 12578065, "suburb": 0, "state": 2344845, "region": 0, "localadmin": 0}, "woe:timezone_id": 56043572, "woe:hash": "7nmbtbd5e40r", "woe:centroid": [-36.658501, -9.7525], "geom:latitude": -9.7525, "geom:longitude": -36.658501, "geom:hash": "7nmbtbd5e40r", "woe:latitude": -9.7525, "geom:centroid": [-36.658501, -9.7525], "woe:longitude": -36.658501, "woe:repo": "woeplanet-airport-br"}, "geometry": {"coordinates": [-36.658501, -9.7525], "type": "Point"}}