{"type": "Feature", "id": 12511145, "geometry": {"type": "Point", "coordinates": [-32.4244, -3.8519]}, "properties": {"woe:id": 12511145, "woe:parent_id": 461591, "woe:name": "Aeroporto Fernando de Noronha", "woe:placetype": 14, "woe:placetype_name": "Airport", "woe:lang": "POR", "iso:country": "BR", "meta:provider": ["geoplanet:7.3.1", "geoplanet:7.3.2", "geoplanet:7.4.0", "geoplanet:7.4.1", "geoplanet:7.5.1", "geoplanet:7.5.2", "geoplanet:7.6.0", "geoplanet:7.8.1", "geoplanet:7.9.0", "geoplanet:7.10.0", "geoplanet:8.0.0", "woeplanet:8.0.0"], "meta:indexed": "2020-08-20T20:58:25.900591", "woe:alias_ENG_V": ["FEN", "Fernando Noronha Airport", "FEN Airport"], "woe:alias_POR_V": ["Aeroporto FEN"], "meta:updated": "2020-10-14T12:05:20.735812", "woe:alias_ENG_P": ["Fernando de Noronha Airport"], "woe:hierarchy": {"continent": 24865673, "country": 23424768, "town": 0, "planet": 1, "county": 12580782, "suburb": 0, "state": 2344860, "region": 0, "localadmin": 0}, "woe:timezone_id": 56043582, "woe:hash": "7r2fn4v309z1", "woe:centroid": [-32.4244, -3.8519], "geom:latitude": -3.8519, "geom:longitude": -32.4244, "geom:hash": "7r2fn4v309z1", "woe:latitude": -3.8519, "geom:centroid": [-32.4244, -3.8519], "woe:longitude": -32.4244, "woe:repo": "woeplanet-airport-br", "geom:area": 0.0, "woe:scale": 19}}