{"type": "Feature", "id": 12523179, "geometry": {"type": "Point", "coordinates": [-60.01667, -15.01667]}, "properties": {"woe:id": 12523179, "woe:parent_id": 455325, "woe:name": "Aeroporto Mato Grosso", "woe:placetype": 14, "woe:placetype_name": "Airport", "woe:lang": "POR", "iso:country": "BR", "meta:provider": ["geoplanet:7.3.1", "geoplanet:7.3.2", "geoplanet:7.4.0", "geoplanet:7.4.1", "geoplanet:7.5.1", "geoplanet:7.5.2", "geoplanet:7.6.0", "geoplanet:7.8.1", "geoplanet:7.9.0", "geoplanet:7.10.0", "geoplanet:8.0.0", "woeplanet:8.0.0"], "meta:indexed": "2020-08-20T20:58:26.096922", "woe:alias_ENG_V": ["MTG Airport", "MTG"], "woe:alias_POR_V": ["Aeroporto MTG"], "meta:updated": "2020-10-14T12:05:20.668224", "woe:alias_ENG_P": ["Mato Grosso Airport"], "woe:hierarchy": {"continent": 24865673, "country": 23424768, "town": 0, "planet": 1, "county": 12579402, "suburb": 0, "state": 2344855, "region": 0, "localadmin": 0}, "woe:timezone_id": 56043575, "woe:hash": "6tm6d631w1z6", "woe:centroid": [-60.01667, -15.01667], "geom:latitude": -15.01667, "geom:longitude": -60.01667, "geom:hash": "6tm6d631w1z6", "woe:latitude": -15.01667, "geom:centroid": [-60.01667, -15.01667], "woe:longitude": -60.01667, "woe:repo": "woeplanet-airport-br", "geom:area": 0.0, "woe:scale": 19}}