{"type": "Feature", "id": 12511361, "properties": {"woe:id": 12511361, "woe:parent_id": 459123, "woe:name": "Aeroporto Urubupunga", "woe:placetype": 14, "woe:placetype_name": "Airport", "woe:lang": "POR", "iso:country": "BR", "meta:provider": ["geoplanet:7.3.1", "geoplanet:7.3.2", "geoplanet:7.4.0", "geoplanet:7.4.1", "geoplanet:7.5.1", "geoplanet:7.5.2", "geoplanet:7.6.0", "geoplanet:7.8.1", "geoplanet:7.9.0", "geoplanet:7.10.0", "geoplanet:8.0.0", "woeplanet:8.0.0"], "meta:indexed": "2020-08-20T20:58:26.081195", "woe:alias_ENG_V": ["URB Airport", "URB"], "woe:alias_POR_V": ["Aeroporto URB"], "meta:updated": "2020-08-22T02:59:07.314291", "woe:alias_ENG_P": ["Urubupunga Airport"], "woe:hierarchy": {"continent": 24865673, "country": 23424768, "town": 0, "planet": 1, "county": 12581923, "suburb": 0, "state": 2344868, "region": 0, "localadmin": 0}, "woe:timezone_id": 28350792, "woe:hash": "6u73f9yjk72y", "woe:centroid": [-51.561401, -20.7756], "geom:latitude": -20.7756, "geom:longitude": -51.561401, "geom:hash": "6u73f9yjk72y", "woe:latitude": -20.7756, "geom:centroid": [-51.561401, -20.7756], "woe:longitude": -51.561401, "woe:repo": "woeplanet-airport-br"}, "geometry": {"coordinates": [-51.561401, -20.7756], "type": "Point"}}