{"type": "Feature", "id": 12511259, "properties": {"woe:id": 12511259, "woe:parent_id": 455974, "woe:name": "Aeroporto Paranavai", "woe:placetype": 14, "woe:placetype_name": "Airport", "woe:lang": "POR", "iso:country": "BR", "meta:provider": ["geoplanet:7.3.1", "geoplanet:7.3.2", "geoplanet:7.4.0", "geoplanet:7.4.1", "geoplanet:7.5.1", "geoplanet:7.5.2", "geoplanet:7.6.0", "geoplanet:7.8.1", "geoplanet:7.9.0", "geoplanet:7.10.0", "geoplanet:8.0.0", "woeplanet:8.0.0"], "meta:indexed": "2020-08-20T20:58:25.995459", "woe:alias_ENG_V": ["PVI Airport", "PVI"], "woe:alias_POR_V": ["Aeroporto PVI"], "meta:updated": "2020-08-22T02:59:07.279151", "woe:alias_ENG_P": ["Paranavai Airport"], "woe:hierarchy": {"continent": 24865673, "country": 23424768, "town": 0, "planet": 1, "county": 12580609, "suburb": 0, "state": 2344859, "region": 0, "localadmin": 0}, "woe:timezone_id": 28350792, "woe:hash": "6gfstsqksdc1", "woe:centroid": [-52.483898, -23.091101], "geom:latitude": -23.091101, "geom:longitude": -52.483898, "geom:hash": "6gfstsqksdc1", "woe:latitude": -23.091101, "geom:centroid": [-52.483898, -23.091101], "woe:longitude": -52.483898, "woe:repo": "woeplanet-airport-br"}, "geometry": {"coordinates": [-52.483898, -23.091101], "type": "Point"}}