{"type": "Feature", "id": 12511086, "geometry": {"type": "Point", "coordinates": [-48.9897, -21.15]}, "properties": {"woe:id": 12511086, "woe:parent_id": 455943, "woe:name": "Aeroporto Catanduva", "woe:placetype": 14, "woe:placetype_name": "Airport", "woe:lang": "POR", "iso:country": "BR", "meta:provider": ["geoplanet:7.3.1", "geoplanet:7.3.2", "geoplanet:7.4.0", "geoplanet:7.4.1", "geoplanet:7.5.1", "geoplanet:7.5.2", "geoplanet:7.6.0", "geoplanet:7.8.1", "geoplanet:7.9.0", "geoplanet:7.10.0", "geoplanet:8.0.0", "woeplanet:8.0.0"], "meta:indexed": "2020-08-20T20:58:25.853081", "woe:alias_ENG_V": ["QDE Airport", "QDE"], "woe:alias_POR_V": ["Aeroporto QDE"], "meta:updated": "2020-10-14T12:05:20.491820", "woe:alias_ENG_P": ["Catanduva Airport"], "woe:hierarchy": {"continent": 24865673, "country": 23424768, "town": 0, "planet": 1, "county": 12581924, "suburb": 0, "state": 2344868, "region": 0, "localadmin": 0}, "woe:timezone_id": 28350792, "woe:hash": "6ujptjyb360p", "woe:centroid": [-48.9897, -21.15], "geom:latitude": -21.15, "geom:longitude": -48.9897, "geom:hash": "6ujptjyb360p", "woe:latitude": -21.15, "geom:centroid": [-48.9897, -21.15], "woe:longitude": -48.9897, "woe:repo": "woeplanet-airport-br", "geom:area": 0.0, "woe:scale": 19}}