{"type": "Feature", "id": 12511296, "properties": {"woe:id": 12511296, "woe:parent_id": 457966, "woe:name": "Aeroporto Russas", "woe:placetype": 14, "woe:placetype_name": "Airport", "woe:lang": "POR", "iso:country": "BR", "meta:provider": ["geoplanet:7.3.1", "geoplanet:7.3.2", "geoplanet:7.4.0", "geoplanet:7.4.1", "geoplanet:7.5.1", "geoplanet:7.5.2", "geoplanet:7.6.0", "geoplanet:7.8.1", "geoplanet:7.9.0", "geoplanet:7.10.0", "geoplanet:8.0.0", "woeplanet:8.0.0"], "meta:indexed": "2020-08-20T20:58:26.026170", "meta:updated": "2020-08-22T02:59:07.290857", "woe:alias_ENG_P": ["Russas Airport"], "woe:hierarchy": {"continent": 24865673, "country": 23424768, "town": 0, "planet": 1, "county": 12578794, "suburb": 0, "state": 2344849, "region": 0, "localadmin": 0}, "woe:timezone_id": 56043570, "woe:hash": "7pjh00cqpsxn", "woe:centroid": [-37.966702, -4.9167], "geom:latitude": -4.9167, "geom:longitude": -37.966702, "geom:hash": "7pjh00cqpsxn", "woe:latitude": -4.9167, "geom:centroid": [-37.966702, -4.9167], "woe:longitude": -37.966702, "woe:repo": "woeplanet-airport-br"}, "geometry": {"coordinates": [-37.966702, -4.9167], "type": "Point"}}