{"type": "Feature", "id": 12511292, "properties": {"woe:id": 12511292, "woe:parent_id": 455825, "woe:name": "Aeroporto Internacional do Rio de Janeiro-Ant\u00f4nio Carlos Jobim", "woe:placetype": 14, "woe:placetype_name": "Airport", "woe:lang": "POR", "iso:country": "BR", "meta:provider": ["geoplanet:7.3.1", "geoplanet:7.3.2", "geoplanet:7.4.0", "geoplanet:7.4.1", "geoplanet:7.5.1", "geoplanet:7.5.2", "geoplanet:7.6.0", "geoplanet:7.8.1", "geoplanet:7.9.0", "geoplanet:7.10.0", "geoplanet:8.0.0", "woeplanet:8.0.0"], "meta:indexed": "2020-08-20T20:58:26.188403", "woe:alias_ENG_V": ["Rio Janeiro International", "GIG", "Rio Janeiro International Airport", "Rio de Janeiro Airport", "Rio de Janeiro International", "GIG Airport", "Rio de Janeiro International Airport", "Rio Janeiro Airport", "Galeao International Airport"], "woe:alias_ENG_P": ["Rio de Janeiro-Antonio Carlos Jobim International Airport"], "woe:alias_POR_V": ["Aeroporto GIG", "Aeroporto Internacional Do Gale\u00e3o", "Aeroporto Internacional Do Galeao", "Aerop Int Do Rio de Janeiro", "Aeroporto Antonio Carlos Jobim"], "meta:updated": "2020-08-22T02:59:07.363039", "woe:alias_POR_S": ["Aeroporto Internacional do Rio de Janeiro-Antonio Carlos Jobim"], "woe:alias_GER_V": ["Internationaler Flughafen Galeao"], "woe:alias_FRE_V": ["Aeroport International de Galeao", "A\u00e9roport International de Gale\u00e3o"], "woe:alias_SPA_V": ["Aeropuerto Internacional de Galean"], "woe:hierarchy": {"continent": 24865673, "country": 23424768, "town": 0, "planet": 1, "county": 12581062, "suburb": 0, "state": 2344862, "region": 0, "localadmin": 0}, "woe:timezone_id": 28350792, "woe:hash": "75cnpyxw68vn", "woe:centroid": [-43.24276, -22.814779], "geom:latitude": -22.814779, "geom:longitude": -43.24276, "geom:hash": "75cnpyxw68vn", "woe:latitude": -22.814779, "geom:centroid": [-43.24276, -22.814779], "woe:longitude": -43.24276, "woe:repo": "woeplanet-airport-br"}, "geometry": {"coordinates": [-43.24276, -22.814779], "type": "Point"}}