{"type": "Feature", "id": 12511297, "geometry": {"type": "Point", "coordinates": [-48.2528, -13.5389]}, "properties": {"woe:id": 12511297, "woe:parent_id": 26797863, "woe:name": "Aeroporto S A Mineracao de Amianto", "woe:placetype": 14, "woe:placetype_name": "Airport", "woe:lang": "POR", "iso:country": "BR", "meta:provider": ["geoplanet:7.3.1", "geoplanet:7.3.2", "geoplanet:7.4.0", "geoplanet:7.4.1", "geoplanet:7.5.1", "geoplanet:7.5.2", "geoplanet:7.6.0", "geoplanet:7.8.1", "geoplanet:7.9.0", "geoplanet:7.10.0", "geoplanet:8.0.0", "woeplanet:8.0.0"], "meta:indexed": "2020-08-20T20:58:26.027092", "meta:updated": "2020-10-14T12:05:20.586372", "woe:alias_ENG_P": ["S A Mineracao de Amianto Airport"], "woe:hierarchy": {"continent": 24865673, "country": 23424768, "town": 0, "planet": 1, "county": 12579014, "suburb": 0, "state": 2344852, "region": 0, "localadmin": 0}, "woe:timezone_id": 28350792, "woe:hash": "6vtdvzr6hq0e", "woe:centroid": [-48.2528, -13.5389], "geom:latitude": -13.5389, "geom:longitude": -48.2528, "geom:hash": "6vtdvzr6hq0e", "woe:latitude": -13.5389, "geom:centroid": [-48.2528, -13.5389], "woe:longitude": -48.2528, "woe:repo": "woeplanet-airport-br", "geom:area": 0.0, "woe:scale": 19}}