{"type": "Feature", "id": 12511313, "properties": {"woe:id": 12511313, "woe:parent_id": 456510, "woe:name": "Aeroporto Sao Borja", "woe:placetype": 14, "woe:placetype_name": "Airport", "woe:lang": "POR", "iso:country": "BR", "meta:provider": ["geoplanet:7.3.1", "geoplanet:7.3.2", "geoplanet:7.4.0", "geoplanet:7.4.1", "geoplanet:7.5.1", "geoplanet:7.5.2", "geoplanet:7.6.0", "geoplanet:7.8.1", "geoplanet:7.9.0", "geoplanet:7.10.0", "geoplanet:8.0.0", "woeplanet:8.0.0"], "meta:indexed": "2020-08-20T20:58:26.039036", "woe:alias_ENG_V": ["QOJ Airport", "QOJ"], "woe:alias_POR_V": ["Aeroporto QOJ"], "meta:updated": "2020-08-22T02:59:07.296629", "woe:alias_ENG_P": ["Sao Borja Airport"], "woe:hierarchy": {"continent": 24865673, "country": 23424768, "town": 0, "planet": 1, "county": 12581486, "suburb": 0, "state": 2344864, "region": 0, "localadmin": 0}, "woe:timezone_id": 28350792, "woe:hash": "6fbjhbnt7pgm", "woe:centroid": [-56.0322, -28.6514], "geom:latitude": -28.6514, "geom:longitude": -56.0322, "geom:hash": "6fbjhbnt7pgm", "woe:latitude": -28.6514, "geom:centroid": [-56.0322, -28.6514], "woe:longitude": -56.0322, "woe:repo": "woeplanet-airport-br"}, "geometry": {"coordinates": [-56.0322, -28.6514], "type": "Point"}}