{"type": "Feature", "id": 12511096, "geometry": {"type": "Point", "coordinates": [-49.302502, -8.3483]}, "properties": {"woe:id": 12511096, "woe:parent_id": 460941, "woe:name": "Aeroporto Conceicao do Araguaia", "woe:placetype": 14, "woe:placetype_name": "Airport", "woe:lang": "POR", "iso:country": "BR", "meta:provider": ["geoplanet:7.3.1", "geoplanet:7.3.2", "geoplanet:7.4.0", "geoplanet:7.4.1", "geoplanet:7.5.1", "geoplanet:7.5.2", "geoplanet:7.6.0", "geoplanet:7.8.1", "geoplanet:7.9.0", "geoplanet:7.10.0", "geoplanet:8.0.0", "woeplanet:8.0.0"], "meta:indexed": "2020-08-20T20:58:25.861389", "woe:alias_ENG_V": ["CDJ Airport", "CDJ"], "woe:alias_POR_V": ["Aeroporto CDJ"], "meta:updated": "2020-10-14T12:05:20.534316", "woe:alias_ENG_P": ["Conceicao do Araguaia Airport"], "woe:hierarchy": {"continent": 24865673, "country": 23424768, "town": 0, "planet": 1, "county": 12580155, "suburb": 0, "state": 2344857, "region": 0, "localadmin": 0}, "woe:timezone_id": 56043569, "woe:hash": "6ysbw05p8kjf", "woe:centroid": [-49.302502, -8.3483], "geom:latitude": -8.3483, "geom:longitude": -49.302502, "geom:hash": "6ysbw05p8kjf", "woe:latitude": -8.3483, "geom:centroid": [-49.302502, -8.3483], "woe:longitude": -49.302502, "woe:repo": "woeplanet-airport-br", "geom:area": 0.0, "woe:scale": 19}}