{"type": "Feature", "id": 28835342, "properties": {"woe:id": 28835342, "woe:parent_id": 461170, "woe:name": "Aeroporto Senadora Eunice Michiles", "woe:placetype": 14, "woe:placetype_name": "Airport", "woe:lang": "POR", "iso:country": "BR", "meta:provider": ["geoplanet:7.3.1", "geoplanet:7.3.2", "geoplanet:7.4.0", "geoplanet:7.4.1", "geoplanet:7.5.1", "geoplanet:7.5.2", "geoplanet:7.6.0", "geoplanet:7.8.1", "geoplanet:7.9.0", "geoplanet:7.10.0", "geoplanet:8.0.0", "woeplanet:8.0.0"], "meta:indexed": "2020-08-20T20:58:26.166087", "meta:updated": "2020-08-22T02:59:07.351603", "woe:alias_ENG_P": ["Senadora Eunice Michiles Airport"], "woe:hierarchy": {"continent": 24865673, "country": 23424768, "town": 0, "planet": 1, "county": 12578221, "suburb": 0, "state": 2344847, "region": 0, "localadmin": 0}, "woe:timezone_id": 56043580, "woe:hash": "6rquqb6j70yn", "woe:centroid": [-68.958298, -3.4694], "geom:latitude": -3.4694, "geom:longitude": -68.958298, "geom:hash": "6rquqb6j70yn", "woe:latitude": -3.4694, "geom:centroid": [-68.958298, -3.4694], "woe:longitude": -68.958298, "woe:repo": "woeplanet-airport-br"}, "geometry": {"coordinates": [-68.958298, -3.4694], "type": "Point"}}