{"type": "Feature", "id": 12511027, "geometry": {"type": "Point", "coordinates": [-42.045601, -16.8514]}, "properties": {"woe:id": 12511027, "woe:parent_id": 456046, "woe:name": "Aeroporto Aracuai", "woe:placetype": 14, "woe:placetype_name": "Airport", "woe:lang": "POR", "iso:country": "BR", "meta:provider": ["geoplanet:7.3.1", "geoplanet:7.3.2", "geoplanet:7.4.0", "geoplanet:7.4.1", "geoplanet:7.5.1", "geoplanet:7.5.2", "geoplanet:7.6.0", "geoplanet:7.8.1", "geoplanet:7.9.0", "geoplanet:7.10.0", "geoplanet:8.0.0", "woeplanet:8.0.0"], "meta:indexed": "2020-08-20T20:58:25.804643", "meta:updated": "2020-10-14T12:05:20.491030", "woe:alias_ENG_P": ["Aracuai Airport"], "woe:hierarchy": {"continent": 24865673, "country": 23424768, "town": 0, "planet": 1, "county": 12579437, "suburb": 0, "state": 2344856, "region": 0, "localadmin": 0}, "woe:timezone_id": 28350792, "woe:hash": "7j405hr36rre", "woe:centroid": [-42.045601, -16.8514], "geom:latitude": -16.8514, "geom:longitude": -42.045601, "geom:hash": "7j405hr36rre", "woe:latitude": -16.8514, "geom:centroid": [-42.045601, -16.8514], "woe:longitude": -42.045601, "woe:repo": "woeplanet-airport-br", "geom:area": 0.0, "woe:scale": 19}}