{"type": "Feature", "id": 12511011, "properties": {"woe:id": 12511011, "woe:parent_id": 455831, "woe:name": "Aerodromo do Nacional de Aviac", "woe:placetype": 14, "woe:placetype_name": "Airport", "woe:lang": "POR", "iso:country": "BR", "meta:provider": ["geoplanet:7.3.1", "geoplanet:7.3.2", "geoplanet:7.4.0", "geoplanet:7.4.1", "geoplanet:7.5.1", "geoplanet:7.5.2", "geoplanet:7.6.0", "geoplanet:7.8.1", "geoplanet:7.9.0", "geoplanet:7.10.0", "geoplanet:8.0.0", "woeplanet:8.0.0"], "meta:indexed": "2020-08-20T20:58:25.791111", "meta:updated": "2020-08-22T02:59:07.191253", "woe:alias_ENG_P": ["Aviac National Aerodrome"], "woe:hierarchy": {"continent": 24865673, "country": 23424768, "town": 0, "planet": 1, "county": 12578971, "suburb": 0, "state": 2344852, "region": 0, "localadmin": 0}, "woe:timezone_id": 28350792, "woe:hash": "6vhckvxbreku", "woe:centroid": [-49.350601, -16.625], "geom:latitude": -16.625, "geom:longitude": -49.350601, "geom:hash": "6vhckvxbreku", "woe:latitude": -16.625, "geom:centroid": [-49.350601, -16.625], "woe:longitude": -49.350601, "woe:repo": "woeplanet-airport-br"}, "geometry": {"coordinates": [-49.350601, -16.625], "type": "Point"}}