{"type": "Feature", "id": 12511107, "properties": {"woe:id": 12511107, "woe:parent_id": 457114, "woe:name": "Aeroporto Curvelo", "woe:placetype": 14, "woe:placetype_name": "Airport", "woe:lang": "POR", "iso:country": "BR", "meta:provider": ["geoplanet:7.3.1", "geoplanet:7.3.2", "geoplanet:7.4.0", "geoplanet:7.4.1", "geoplanet:7.5.1", "geoplanet:7.5.2", "geoplanet:7.6.0", "geoplanet:7.8.1", "geoplanet:7.9.0", "geoplanet:7.10.0", "geoplanet:8.0.0", "woeplanet:8.0.0"], "meta:indexed": "2020-08-20T20:58:25.867660", "meta:updated": "2020-08-22T02:59:07.225792", "woe:alias_ENG_P": ["Curvelo Airport"], "woe:hierarchy": {"continent": 24865673, "country": 23424768, "town": 0, "planet": 1, "county": 12579612, "suburb": 0, "state": 2344856, "region": 0, "localadmin": 0}, "woe:timezone_id": 28350792, "woe:hash": "7h8mhrg43nt7", "woe:centroid": [-44.4575, -18.7656], "geom:latitude": -18.7656, "geom:longitude": -44.4575, "geom:hash": "7h8mhrg43nt7", "woe:latitude": -18.7656, "geom:centroid": [-44.4575, -18.7656], "woe:longitude": -44.4575, "woe:repo": "woeplanet-airport-br"}, "geometry": {"coordinates": [-44.4575, -18.7656], "type": "Point"}}