{"type": "Feature", "id": 12511181, "geometry": {"type": "Point", "coordinates": [-41.8494, -11.3389]}, "properties": {"woe:id": 12511181, "woe:parent_id": 456247, "woe:name": "Aeroporto Irece", "woe:placetype": 14, "woe:placetype_name": "Airport", "woe:lang": "POR", "iso:country": "BR", "meta:provider": ["geoplanet:7.3.1", "geoplanet:7.3.2", "geoplanet:7.4.0", "geoplanet:7.4.1", "geoplanet:7.5.1", "geoplanet:7.5.2", "geoplanet:7.6.0", "geoplanet:7.8.1", "geoplanet:7.9.0", "geoplanet:7.10.0", "geoplanet:8.0.0", "woeplanet:8.0.0"], "meta:indexed": "2020-08-20T20:58:25.929527", "woe:alias_ENG_V": ["IRE Airport", "IRE"], "woe:alias_POR_V": ["Aeroporto IRE"], "meta:updated": "2020-10-14T12:05:20.760785", "woe:alias_ENG_P": ["Irece Airport"], "woe:hierarchy": {"continent": 24865673, "country": 23424768, "town": 0, "planet": 1, "county": 12578403, "suburb": 0, "state": 2344848, "region": 0, "localadmin": 0}, "woe:timezone_id": 56043573, "woe:hash": "7jfprxy4n7cd", "woe:centroid": [-41.8494, -11.3389], "geom:latitude": -11.3389, "geom:longitude": -41.8494, "geom:hash": "7jfprxy4n7cd", "woe:latitude": -11.3389, "geom:centroid": [-41.8494, -11.3389], "woe:longitude": -41.8494, "woe:repo": "woeplanet-airport-br", "geom:area": 0.0, "woe:scale": 19}}