{"type": "Feature", "id": 12511241, "properties": {"woe:id": 12511241, "woe:parent_id": 456356, "woe:name": "Aeroporto Navirai", "woe:placetype": 14, "woe:placetype_name": "Airport", "woe:lang": "POR", "iso:country": "BR", "meta:provider": ["geoplanet:7.3.1", "geoplanet:7.3.2", "geoplanet:7.4.0", "geoplanet:7.4.1", "geoplanet:7.5.1", "geoplanet:7.5.2", "geoplanet:7.6.0", "geoplanet:7.8.1", "geoplanet:7.9.0", "geoplanet:7.10.0", "geoplanet:8.0.0", "woeplanet:8.0.0"], "meta:indexed": "2020-08-20T20:58:25.979649", "meta:updated": "2020-08-22T02:59:07.272552", "woe:alias_ENG_P": ["Navirai Airport"], "woe:hierarchy": {"continent": 24865673, "country": 23424768, "town": 0, "planet": 1, "county": 12579151, "suburb": 0, "state": 2344853, "region": 0, "localadmin": 0}, "woe:timezone_id": 56043574, "woe:hash": "6gckznu9f4h0", "woe:centroid": [-54.178299, -23.033899], "geom:latitude": -23.033899, "geom:longitude": -54.178299, "geom:hash": "6gckznu9f4h0", "woe:latitude": -23.033899, "geom:centroid": [-54.178299, -23.033899], "woe:longitude": -54.178299, "woe:repo": "woeplanet-airport-br"}, "geometry": {"coordinates": [-54.178299, -23.033899], "type": "Point"}}