{"type": "Feature", "id": 12511046, "properties": {"woe:id": 12511046, "woe:parent_id": 456778, "woe:name": "Aeroporto Barreirinha", "woe:placetype": 14, "woe:placetype_name": "Airport", "woe:lang": "POR", "iso:country": "BR", "meta:provider": ["geoplanet:7.3.1", "geoplanet:7.3.2", "geoplanet:7.4.0", "geoplanet:7.4.1", "geoplanet:7.5.1", "geoplanet:7.5.2", "geoplanet:7.6.0", "geoplanet:7.8.1", "geoplanet:7.9.0", "geoplanet:7.10.0", "geoplanet:8.0.0", "woeplanet:8.0.0"], "meta:indexed": "2020-08-20T20:58:25.820843", "meta:updated": "2020-08-22T02:59:07.202705", "woe:alias_ENG_P": ["Barreirinha Airport"], "woe:hierarchy": {"continent": 24865673, "country": 23424768, "town": 0, "planet": 1, "county": 12578177, "suburb": 0, "state": 2344847, "region": 0, "localadmin": 0}, "woe:timezone_id": 56043581, "woe:hash": "6xx2jej3k1jg", "woe:centroid": [-57.055599, -2.7958], "geom:latitude": -2.7958, "geom:longitude": -57.055599, "geom:hash": "6xx2jej3k1jg", "woe:latitude": -2.7958, "geom:centroid": [-57.055599, -2.7958], "woe:longitude": -57.055599, "woe:repo": "woeplanet-airport-br"}, "geometry": {"coordinates": [-57.055599, -2.7958], "type": "Point"}}