{"type": "Feature", "id": 12511257, "properties": {"woe:id": 12511257, "woe:parent_id": 455089, "woe:name": "Aeroporto da Pampulha", "woe:placetype": 14, "woe:placetype_name": "Airport", "woe:lang": "POR", "iso:country": "BR", "meta:provider": ["geoplanet:7.3.1", "geoplanet:7.3.2", "geoplanet:7.4.0", "geoplanet:7.4.1", "geoplanet:7.5.1", "geoplanet:7.5.2", "geoplanet:7.6.0", "geoplanet:7.8.1", "geoplanet:7.9.0", "geoplanet:7.10.0", "geoplanet:8.0.0", "woeplanet:8.0.0"], "meta:indexed": "2020-08-20T20:58:26.186649", "woe:alias_ENG_V": ["PLU Airport", "PLU"], "woe:alias_POR_V": ["Aeroporto PLU", "Aer. Carlos Drummond de Andrade", "Aeroporto de Belo Horizonte"], "meta:updated": "2020-08-22T02:59:07.362163", "woe:alias_ENG_P": ["Pampulha Airport"], "woe:hierarchy": {"continent": 24865673, "country": 23424768, "town": 0, "planet": 1, "county": 12579464, "suburb": 0, "state": 2344856, "region": 0, "localadmin": 0}, "woe:timezone_id": 28350792, "woe:hash": "7h2xpf0dpgzf", "woe:centroid": [-43.955269, -19.851931], "geom:latitude": -19.851931, "geom:longitude": -43.955269, "geom:hash": "7h2xpf0dpgzf", "woe:latitude": -19.851931, "geom:centroid": [-43.955269, -19.851931], "woe:longitude": -43.955269, "woe:repo": "woeplanet-airport-br"}, "geometry": {"coordinates": [-43.955269, -19.851931], "type": "Point"}}