{"type": "Feature", "id": 12511362, "geometry": {"type": "Point", "coordinates": [-57.7556, -2.5294]}, "properties": {"woe:id": 12511362, "woe:parent_id": 458235, "woe:name": "Aeroporto Urucara", "woe:placetype": 14, "woe:placetype_name": "Airport", "woe:lang": "POR", "iso:country": "BR", "meta:provider": ["geoplanet:7.3.1", "geoplanet:7.3.2", "geoplanet:7.4.0", "geoplanet:7.4.1", "geoplanet:7.5.1", "geoplanet:7.5.2", "geoplanet:7.6.0", "geoplanet:7.8.1", "geoplanet:7.9.0", "geoplanet:7.10.0", "geoplanet:8.0.0", "woeplanet:8.0.0"], "meta:indexed": "2020-08-20T20:58:26.082048", "meta:updated": "2020-10-14T12:05:20.695797", "woe:alias_ENG_P": ["Urucara Airport"], "woe:hierarchy": {"continent": 24865673, "country": 23424768, "town": 0, "planet": 1, "county": 12578229, "suburb": 0, "state": 2344847, "region": 0, "localadmin": 0}, "woe:timezone_id": 56043581, "woe:hash": "6xwctex9hvxm", "woe:centroid": [-57.7556, -2.5294], "geom:latitude": -2.5294, "geom:longitude": -57.7556, "geom:hash": "6xwctex9hvxm", "woe:latitude": -2.5294, "geom:centroid": [-57.7556, -2.5294], "woe:longitude": -57.7556, "woe:repo": "woeplanet-airport-br", "geom:area": 0.0, "woe:scale": 19}}