{"type": "Feature", "id": 56049645, "geometry": {"type": "Point", "coordinates": [-36.010578, -8.28502]}, "properties": {"woe:id": 56049645, "woe:parent_id": 455852, "woe:name": "Aeroporto Oscar Laranjeira", "woe:placetype": 14, "woe:placetype_name": "Airport", "woe:lang": "POR", "iso:country": "BR", "meta:provider": ["geoplanet:7.3.1", "geoplanet:7.3.2", "geoplanet:7.4.0", "geoplanet:7.4.1", "geoplanet:7.5.1", "geoplanet:7.5.2", "geoplanet:7.6.0", "geoplanet:7.8.1", "geoplanet:7.9.0", "geoplanet:7.10.0", "geoplanet:8.0.0", "woeplanet:8.0.0"], "meta:indexed": "2020-08-20T20:58:26.171498", "meta:updated": "2020-10-14T12:05:20.479892", "woe:hierarchy": {"continent": 24865673, "country": 23424768, "town": 0, "planet": 1, "county": 12580768, "suburb": 0, "state": 2344860, "region": 0, "localadmin": 0}, "woe:timezone_id": 56043582, "woe:hash": "7nw2uecbk8qf", "woe:centroid": [-36.010578, -8.28502], "geom:latitude": -8.28502, "geom:longitude": -36.010578, "geom:hash": "7nw2uecbk8qf", "woe:latitude": -8.28502, "geom:centroid": [-36.010578, -8.28502], "woe:longitude": -36.010578, "woe:repo": "woeplanet-airport-br", "geom:area": 0.0, "woe:scale": 19}}