{"type": "Feature", "id": 12523097, "geometry": {"type": "Point", "coordinates": [-46.849998, -11.61667]}, "properties": {"woe:id": 12523097, "woe:parent_id": 456173, "woe:name": "Aeroporto Dianopolis", "woe:placetype": 14, "woe:placetype_name": "Airport", "woe:lang": "POR", "iso:country": "BR", "meta:provider": ["geoplanet:7.3.1", "geoplanet:7.3.2", "geoplanet:7.4.0", "geoplanet:7.4.1", "geoplanet:7.5.1", "geoplanet:7.5.2", "geoplanet:7.6.0", "geoplanet:7.8.1", "geoplanet:7.9.0", "geoplanet:7.10.0", "geoplanet:8.0.0", "woeplanet:8.0.0"], "meta:indexed": "2020-08-20T20:58:26.096032", "woe:alias_ENG_V": ["DNO Airport", "DNO"], "woe:alias_POR_V": ["Aeroporto DNO"], "meta:updated": "2020-10-14T12:05:20.544380", "woe:alias_ENG_P": ["Dianopolis Airport"], "woe:hierarchy": {"continent": 24865673, "country": 23424768, "town": 0, "planet": 1, "county": 12582484, "suburb": 0, "state": 2344870, "region": 0, "localadmin": 0}, "woe:timezone_id": 56043571, "woe:hash": "6vytvvhzgzv8", "woe:centroid": [-46.849998, -11.61667], "geom:latitude": -11.61667, "geom:longitude": -46.849998, "geom:hash": "6vytvvhzgzv8", "woe:latitude": -11.61667, "geom:centroid": [-46.849998, -11.61667], "woe:longitude": -46.849998, "woe:repo": "woeplanet-airport-br", "geom:area": 0.0, "woe:scale": 19}}