{"type": "Feature", "id": 12523652, "geometry": {"type": "Point", "coordinates": [-51.1833, -19.6667]}, "properties": {"woe:id": 12523652, "woe:parent_id": 456390, "woe:name": "Aeroporto Paranaiba", "woe:placetype": 14, "woe:placetype_name": "Airport", "woe:lang": "POR", "iso:country": "BR", "meta:provider": ["geoplanet:7.3.1", "geoplanet:7.3.2", "geoplanet:7.4.0", "geoplanet:7.4.1", "geoplanet:7.5.1", "geoplanet:7.5.2", "geoplanet:7.6.0", "geoplanet:7.8.1", "geoplanet:7.9.0", "geoplanet:7.10.0", "geoplanet:8.0.0", "woeplanet:8.0.0"], "meta:indexed": "2020-08-20T20:58:26.137606", "woe:alias_ENG_V": ["PBB Airport", "PBB"], "woe:alias_POR_V": ["Aeroporto PBB"], "meta:updated": "2020-10-14T12:05:20.625573", "woe:alias_ENG_P": ["Paranaiba Airport"], "woe:hierarchy": {"continent": 24865673, "country": 23424768, "town": 0, "planet": 1, "county": 12579154, "suburb": 0, "state": 2344853, "region": 0, "localadmin": 0}, "woe:timezone_id": 56043574, "woe:hash": "6ue857c3ntmk", "woe:centroid": [-51.1833, -19.6667], "geom:latitude": -19.6667, "geom:longitude": -51.1833, "geom:hash": "6ue857c3ntmk", "woe:latitude": -19.6667, "geom:centroid": [-51.1833, -19.6667], "woe:longitude": -51.1833, "woe:repo": "woeplanet-airport-br", "geom:area": 0.0, "woe:scale": 19}}