{"type": "Feature", "id": 12511239, "properties": {"woe:id": 12511239, "woe:parent_id": 457632, "woe:name": "Aeroporto Mostardas", "woe:placetype": 14, "woe:placetype_name": "Airport", "woe:lang": "POR", "iso:country": "BR", "meta:provider": ["geoplanet:7.3.1", "geoplanet:7.3.2", "geoplanet:7.4.0", "geoplanet:7.4.1", "geoplanet:7.5.1", "geoplanet:7.5.2", "geoplanet:7.6.0", "geoplanet:7.8.1", "geoplanet:7.9.0", "geoplanet:7.10.0", "geoplanet:8.0.0", "woeplanet:8.0.0"], "meta:indexed": "2020-08-20T20:58:25.977787", "meta:updated": "2020-08-22T02:59:07.271693", "woe:alias_ENG_P": ["Mostardas Airport"], "woe:hierarchy": {"continent": 24865673, "country": 23424768, "town": 0, "planet": 1, "county": 12581409, "suburb": 0, "state": 2344864, "region": 0, "localadmin": 0}, "woe:timezone_id": 28350792, "woe:hash": "6f7z13xhfszg", "woe:centroid": [-50.9119, -31.1042], "geom:latitude": -31.1042, "geom:longitude": -50.9119, "geom:hash": "6f7z13xhfszg", "woe:latitude": -31.1042, "geom:centroid": [-50.9119, -31.1042], "woe:longitude": -50.9119, "woe:repo": "woeplanet-airport-br"}, "geometry": {"coordinates": [-50.9119, -31.1042], "type": "Point"}}