{"type": "Feature", "id": 12511058, "geometry": {"type": "Point", "coordinates": [-47.912201, -15.8622]}, "properties": {"woe:id": 12511058, "woe:parent_id": 28358233, "woe:name": "Aeroporto Internacional Juscelino Kubitschek", "woe:placetype": 14, "woe:placetype_name": "Airport", "woe:lang": "POR", "iso:country": "BR", "meta:provider": ["geoplanet:7.3.1", "geoplanet:7.3.2", "geoplanet:7.4.0", "geoplanet:7.4.1", "geoplanet:7.5.1", "geoplanet:7.5.2", "geoplanet:7.6.0", "geoplanet:7.8.1", "geoplanet:7.9.0", "geoplanet:7.10.0", "geoplanet:8.0.0", "woeplanet:8.0.0"], "meta:indexed": "2020-08-20T20:58:26.174223", "woe:alias_ENG_V": ["Brasilia International Airport", "Brasilia International", "Brasilia Airport", "BSB", "BSB Airport"], "woe:alias_POR_V": ["Aeroporto BSB"], "meta:updated": "2020-10-14T12:05:20.499497", "woe:alias_ENG_P": ["Juscelino Kubitschek International Airport"], "woe:hierarchy": {"continent": 24865673, "country": 23424768, "town": 0, "planet": 1, "county": 28358221, "suburb": 0, "state": 2344850, "region": 0, "localadmin": 0}, "woe:timezone_id": 28350792, "woe:hash": "6vjvv8r7uz9e", "woe:centroid": [-47.912201, -15.8622], "geom:latitude": -15.8622, "geom:longitude": -47.912201, "geom:hash": "6vjvv8r7uz9e", "woe:latitude": -15.8622, "geom:centroid": [-47.912201, -15.8622], "woe:longitude": -47.912201, "woe:repo": "woeplanet-airport-br", "geom:area": 0.0, "woe:scale": 19}}