{"type": "Feature", "id": 12511150, "properties": {"woe:id": 12511150, "woe:parent_id": 457197, "woe:name": "Aeroporto Paulo Abdala", "woe:placetype": 14, "woe:placetype_name": "Airport", "woe:lang": "POR", "iso:country": "BR", "meta:provider": ["geoplanet:7.3.1", "geoplanet:7.3.2", "geoplanet:7.4.0", "geoplanet:7.4.1", "geoplanet:7.5.1", "geoplanet:7.5.2", "geoplanet:7.6.0", "geoplanet:7.8.1", "geoplanet:7.9.0", "geoplanet:7.10.0", "geoplanet:8.0.0", "woeplanet:8.0.0"], "meta:indexed": "2020-08-20T20:58:25.904104", "woe:alias_ENG_V": ["FBE", "Francisco Beltrao Airport", "FBE Airport"], "woe:alias_POR_V": ["Aeroporto FBE"], "meta:updated": "2020-08-22T02:59:07.239835", "woe:alias_ENG_P": ["Paulo Abdala Airport"], "woe:hierarchy": {"continent": 24865673, "country": 23424768, "town": 0, "planet": 1, "county": 12580497, "suburb": 0, "state": 2344859, "region": 0, "localadmin": 0}, "woe:timezone_id": 28350792, "woe:hash": "6g67b0e0dz06", "woe:centroid": [-53.081699, -26.0567], "geom:latitude": -26.0567, "geom:longitude": -53.081699, "geom:hash": "6g67b0e0dz06", "woe:latitude": -26.0567, "geom:centroid": [-53.081699, -26.0567], "woe:longitude": -53.081699, "woe:repo": "woeplanet-airport-br"}, "geometry": {"coordinates": [-53.081699, -26.0567], "type": "Point"}}