{"type": "Feature", "id": 12511251, "properties": {"woe:id": 12511251, "woe:parent_id": 442172, "woe:name": "Aeroporto Oriximina", "woe:placetype": 14, "woe:placetype_name": "Airport", "woe:lang": "POR", "iso:country": "BR", "meta:provider": ["geoplanet:7.3.1", "geoplanet:7.3.2", "geoplanet:7.4.0", "geoplanet:7.4.1", "geoplanet:7.5.1", "geoplanet:7.5.2", "geoplanet:7.6.0", "geoplanet:7.8.1", "geoplanet:7.9.0", "geoplanet:7.10.0", "geoplanet:8.0.0", "woeplanet:8.0.0"], "meta:indexed": "2020-08-20T20:58:25.988773", "woe:alias_ENG_V": ["ORX Airport", "ORX"], "woe:alias_POR_V": ["Aeroporto ORX"], "meta:updated": "2020-08-22T02:59:07.276936", "woe:alias_ENG_P": ["Oriximina Airport"], "woe:hierarchy": {"continent": 24865673, "country": 23424768, "town": 0, "planet": 1, "county": 12580187, "suburb": 0, "state": 2344857, "region": 0, "localadmin": 0}, "woe:timezone_id": 56043576, "woe:hash": "6z8mbsc5fhh2", "woe:centroid": [-55.875, -1.775], "geom:latitude": -1.775, "geom:longitude": -55.875, "geom:hash": "6z8mbsc5fhh2", "woe:latitude": -1.775, "geom:centroid": [-55.875, -1.775], "woe:longitude": -55.875, "woe:repo": "woeplanet-airport-br"}, "geometry": {"coordinates": [-55.875, -1.775], "type": "Point"}}