{"type": "Feature", "id": 12523512, "geometry": {"type": "Point", "coordinates": [-40.843899, -2.903]}, "properties": {"woe:id": 12523512, "woe:parent_id": 456111, "woe:name": "Aeroporto Camocim", "woe:placetype": 14, "woe:placetype_name": "Airport", "woe:lang": "POR", "iso:country": "BR", "meta:provider": ["geoplanet:7.3.1", "geoplanet:7.3.2", "geoplanet:7.4.0", "geoplanet:7.4.1", "geoplanet:7.5.1", "geoplanet:7.5.2", "geoplanet:7.6.0", "geoplanet:7.8.1", "geoplanet:7.9.0", "geoplanet:7.10.0", "geoplanet:8.0.0", "woeplanet:8.0.0"], "meta:indexed": "2020-08-20T20:58:26.113095", "woe:alias_ENG_V": ["CMC Airport", "CMC"], "woe:alias_POR_V": ["Aeroporto CMC"], "meta:updated": "2020-10-14T12:05:20.662220", "woe:alias_ENG_P": ["Camocim Airport"], "woe:hierarchy": {"continent": 24865673, "country": 23424768, "town": 0, "planet": 1, "county": 12578676, "suburb": 0, "state": 2344849, "region": 0, "localadmin": 0}, "woe:timezone_id": 56043570, "woe:hash": "7p6zqxd2u1td", "woe:centroid": [-40.843899, -2.903], "geom:latitude": -2.903, "geom:longitude": -40.843899, "geom:hash": "7p6zqxd2u1td", "woe:latitude": -2.903, "geom:centroid": [-40.843899, -2.903], "woe:longitude": -40.843899, "woe:repo": "woeplanet-airport-br", "geom:area": 0.0, "woe:scale": 19}}